{
  "2": {
    "nome": "ADVAN GABRIEL SEBASTIÃO FAQUINETI",
    "foto": "ADVAN GABRIEL SEBASTIÃO FAQUINETI.jpg"
  },
  "3": {
    "nome": "ANA LÍVIA DA RÓSA FARIAS",
    "foto": "ANA LÍVIA DA RÓSA FARIAS.jpg"
  },
  "4": {
    "nome": "ANA VITORIA DE OLIVEIRA",
    "foto": "ANA VITORIA DE OLIVEIRA.jpg"
  },
  "5": {
    "nome": "ANDRÉ KAUAN MACEDO DE SOUZA",
    "foto": "ANDRÉ KAUAN MACEDO DE SOUZA.jpg"
  },
  "7": {
    "nome": "CHRISTYAN MIGUEL MUNIZ DE OLIVEIRA",
    "foto": "CHRISTYAN MIGUEL MUNIZ DE OLIVEIRA.jpg"
  },
  "9": {
    "nome": "DÉBORA LUANA DA SILVA",
    "foto": "DÉBORA LUANA DA SILVA.jpg"
  },
  "11": {
    "nome": "GABRIEL REIS MARTINS",
    "foto": "GABRIEL REIS MARTINS.jpg"
  },
  "12": {
    "nome": "GABRIELLE VICTORIA FERREIRA",
    "foto": "GABRIELLE VICTORIA FERREIRA.jpg"
  },
  "14": {
    "nome": "HENRIQUE MARTINS",
    "foto": "HENRIQUE MARTINS.jpg"
  },
  "15": {
    "nome": "JHULLIA ANTONYELLY ANDRADE JESUS",
    "foto": "JHULLIA ANTONYELLY ANDRADE JESUS.jpg"
  },
  "17": {
    "nome": "JOHN WINCHESTER PIQUER",
    "foto": "JOHN WINCHESTER PIQUER.jpg"
  },
  "18": {
    "nome": "JUAN HENRIQUE DE CARVALHO",
    "foto": "JUAN HENRIQUE DE CARVALHO.jpg"
  },
  "19": {
    "nome": "JÚLIA NICOLY TEIXEIRA",
    "foto": "JÚLIA NICOLY TEIXEIRA.jpg"
  },
  "21": {
    "nome": "LARA REIS DE OLIVEIRA",
    "foto": "LARA REIS DE OLIVEIRA.jpg"
  },
  "22": {
    "nome": "LAURA BUZATO OLIVEIRA",
    "foto": "LAURA BUZATO OLIVEIRA.jpg"
  },
  "23": {
    "nome": "LETÍCIA SILVA ALVES",
    "foto": "LETÍCIA SILVA ALVES.jpg"
  },
  "24": {
    "nome": "LUCAS DONISETI LASARINO",
    "foto": "LUCAS DONISETI LASARINO.jpg"
  },
  "25": {
    "nome": "LUIZ GUSTAVO TAGLIOLATTO DOS SANTOS",
    "foto": "LUIZ GUSTAVO TAGLIOLATTO DOS SANTOS.jpg"
  },
  "26": {
    "nome": "LUIZ OCTÁVIO RODRIGUES TRESSOLDI",
    "foto": "LUIZ OCTÁVIO RODRIGUES TRESSOLDI.jpg"
  },
  "27": {
    "nome": "MARIANNY DE OLIVEIRA MACHADO",
    "foto": "MARIANNY DE OLIVEIRA MACHADO.jpg"
  },
  "28": {
    "nome": "MIGUEL GIMENEZ PEREIRA",
    "foto": "MIGUEL GIMENEZ PEREIRA.jpg"
  },
  "29": {
    "nome": "NATALIA LUIZA MALTA",
    "foto": "NATALIA LUIZA MALTA.jpg"
  },
  "30": {
    "nome": "NÍCOLAS GABRIEL ALVES MATOS DA SILVA",
    "foto": "NÍCOLAS GABRIEL ALVES MATOS DA SILVA.jpg"
  },
  "31": {
    "nome": "NICOLLY GABRIELLY MARIANO PALOMO",
    "foto": "NICOLLY GABRIELLY MARIANO PALOMO.jpg"
  },
  "32": {
    "nome": "NICOLLY RAMOS FERREIRA DE SOUZA",
    "foto": "NICOLLY RAMOS FERREIRA DE SOUZA.jpg"
  },
  "33": {
    "nome": "RAFAEL VINÍCIUS REFUNDINI",
    "foto": "RAFAEL VINÍCIUS REFUNDINI.jpg"
  },
  "34": {
    "nome": "TALITA GABRIELA SILVA FERREIRA",
    "foto": "TALITA GABRIELA SILVA FERREIRA.jpg"
  },
  "35": {
    "nome": "THAYLA EDUARDA MOTERANI DA SILVA",
    "foto": "THAYLA EDUARDA MOTERANI DA SILVA.jpg"
  },
  "37": {
    "nome": "WÁLISSON ARAUJO JULIARI",
    "foto": "WÁLISSON ARAUJO JULIARI.jpg"
  },
  "38": {
    "nome": "WARLEY RIQUELME DA SILVA",
    "foto": "WARLEY RIQUELME DA SILVA.jpg"
  },
  "39": {
    "nome": "WÉLLINGTON DE OLIVEIRA LIMA",
    "foto": "WÉLLINGTON DE OLIVEIRA LIMA.jpg"
  },
  "40": {
    "nome": "WENDEL ALEXSANDRO DOS SANTOS BENTO",
    "foto": "WENDEL ALEXSANDRO DOS SANTOS BENTO.jpg"
  },
  "41": {
    "nome": "HENRIQUE EMANUEL TEODORO",
    "foto": "HENRIQUE EMANUEL TEODORO.jpg"
  }
}